lthread/__init__.py
lthread/core.py
lthread/glib.py
lthread/io.py
lthread/subprocess.py
lthread-1.0.2.dist-info/DESCRIPTION.rst
lthread-1.0.2.dist-info/METADATA
lthread-1.0.2.dist-info/RECORD
lthread-1.0.2.dist-info/WHEEL
lthread-1.0.2.dist-info/metadata.json
lthread-1.0.2.dist-info/top_level.txt
