Metadata-Version: 2.0
Name: lthread
Version: 1.0.2
Summary: lightweight threads in Python using extended generators
Home-page: UNKNOWN
Author: Katie Stafford
Author-email: katie@ktpanda.org
License: MIT License
Platform: UNKNOWN
Classifier: Programming Language :: Python
Classifier: Development Status :: 3 - Alpha
Classifier: Environment :: Other Environment
Classifier: Intended Audience :: Developers
Classifier: License :: OSI Approved :: MIT License
Classifier: Topic :: Software Development :: Libraries :: Python Modules
Classifier: Operating System :: Unix
Classifier: Operating System :: Microsoft :: Windows
